Workbook
Name BALANCESHEET: 'BALANCE SHEET'!$A$3:$E$15
Name CAHRTS: Table849[#All]
Name CHARTS: Table849[#All]
Name DEPRECIATION: DEPRECIATION!$A$4:$D$25
Name FILTER: FILTER!$A$3:$O$30
Name FINANCIAL: 'FINACNICAL '!$A$3:$D$23
Name IFFUCNTION: 'IF FUNCTION'!$A$3:$H$27
Name IFFUNCTION2: 'IF FUNCITON 2'!$A$3:$F$25
Name IFSUM: 'IF&SUM'!$A$3:$I$22
Name INDEX2: 'SALES REPORT'!$A$3:$M$18
Name indexsales: #REF!
Name MARKSHEET: MARKSHEET!$A$3:$N$28
Name PARETOS: 'PARETOS CHART'!$A$3:$D$30
Name PARETOS2: #REF!
Name SPEEDOMETER: SPEEDOMETER!$A$3:$C$9
Name STUDENTLIST: 'STUDENT LIST'!$A$4:$I$20
Name SUMIF: SUMIF!$A$3:$E$44
Name VLOOUKUP: VLOOKUP!$A$3:$E$25

Sheet MARKSHEET
A1: MARKSHEET
A3: NAME | B3: MATHS | C3: ENG | D3: HINDI | E3: SCI | F3: SST | G3: ECO | H3: TOTAL | I3: AVG | J3: GRADE | K3: MIN | L3: MAX | M3: RANK | N3: ROUND
A4: ROHAN | B4: 23 | C4: 58 | D4: 59 | E4: 47 | F4: 64 | G4: 80 | H4: =SUM(B4:G4) -> 331 | I4: =AVERAGE(B4:G4) -> 55.166667 | J4: =IF(I4>75,"A","B") -> B | K4: =MIN(B4:G4) -> 23 | L4: =MAX(B4:G4) -> 80 | M4: =RANK(I4,$I$4:$I$28) -> 15 | N4: =ROUND(I4,0) -> 55
A5: SOHAN | B5: 65 | C5: 96 | D5: 84 | E5: 62 | F5: 31 | G5: 27 | H5: =SUM(B5:G5) -> 365 | I5: =AVERAGE(B5:G5) -> 60.833333 | J5: =IF(I5>75,"A","B") -> B | K5: =MIN(B5:G5) -> 27 | L5: =MAX(B5:G5) -> 96 | M5: =RANK(I5,$I$4:$I$28) -> 12 | N5: =ROUND(I5,0) -> 61
A6: KARAN | B6: 98 | C6: 98 | D6: 23 | E6: 69 | F6: 62 | G6: 71 | H6: =SUM(B6:G6) -> 421 | I6: =AVERAGE(B6:G6) -> 70.166667 | J6: =IF(I6>75,"A","B") -> B | K6: =MIN(B6:G6) -> 23 | L6: =MAX(B6:G6) -> 98 | M6: =RANK(I6,$I$4:$I$28) -> 3 | N6: =ROUND(I6,0) -> 70
A7: KAVITA | B7: 45 | C7: 65 | D7: 43 | E7: 30 | F7: 21 | G7: 51 | H7: =SUM(B7:G7) -> 255 | I7: =AVERAGE(B7:G7) -> 42.5 | J7: =IF(I7>75,"A","B") -> B | K7: =MIN(B7:G7) -> 21 | L7: =MAX(B7:G7) -> 65 | M7: =RANK(I7,$I$4:$I$28) -> 25 | N7: =ROUND(I7,0) -> 43
A8: DEEPAK | B8: 89 | C8: 85 | D8: 21 | E8: 40 | F8: 37 | G8: 51 | H8: =SUM(B8:G8) -> 323 | I8: =AVERAGE(B8:G8) -> 53.833333 | J8: =IF(I8>75,"A","B") -> B | K8: =MIN(B8:G8) -> 21 | L8: =MAX(B8:G8) -> 89 | M8: =RANK(I8,$I$4:$I$28) -> 17 | N8: =ROUND(I8,0) -> 54
A9: DEEPIKA | B9: 57 | C9: 87 | D9: 24 | E9: 47 | F9: 64 | G9: 44 | H9: =SUM(B9:G9) -> 323 | I9: =AVERAGE(B9:G9) -> 53.833333 | J9: =IF(I9>75,"A","B") -> B | K9: =MIN(B9:G9) -> 24 | L9: =MAX(B9:G9) -> 87 | M9: =RANK(I9,$I$4:$I$28) -> 17 | N9: =ROUND(I9,0) -> 54
A10: LALITA | B10: 85 | C10: 98 | D10: 67 | E10: 83 | F10: 83 | G10: 52 | H10: =SUM(B10:G10) -> 468 | I10: =AVERAGE(B10:G10) -> 78 | J10: =IF(I10>75,"A","B") -> A | K10: =MIN(B10:G10) -> 52 | L10: =MAX(B10:G10) -> 98 | M10: =RANK(I10,$I$4:$I$28) -> 1 | N10: =ROUND(I10,0) -> 78
A11: GAGAN | B11: 74 | C11: 65 | D11: 83 | E11: 28 | F11: 63 | G11: 41 | H11: =SUM(B11:G11) -> 354 | I11: =AVERAGE(B11:G11) -> 59 | J11: =IF(I11>75,"A","B") -> B | K11: =MIN(B11:G11) -> 28 | L11: =MAX(B11:G11) -> 83 | M11: =RANK(I11,$I$4:$I$28) -> 13 | N11: =ROUND(I11,0) -> 59
A12: MANISH | B12: 65 | C12: 78 | D12: 68 | E12: 70 | F12: 44 | G12: 46 | H12: =SUM(B12:G12) -> 371 | I12: =AVERAGE(B12:G12) -> 61.833333 | J12: =IF(I12>75,"A","B") -> B | K12: =MIN(B12:G12) -> 44 | L12: =MAX(B12:G12) -> 78 | M12: =RANK(I12,$I$4:$I$28) -> 11 | N12: =ROUND(I12,0) -> 62
A13: RIYA | B13: 98 | C13: 58 | D13: 68 | E13: 73 | F13: 52 | G13: 67 | H13: =SUM(B13:G13) -> 416 | I13: =AVERAGE(B13:G13) -> 69.333333 | J13: =IF(I13>75,"A","B") -> B | K13: =MIN(B13:G13) -> 52 | L13: =MAX(B13:G13) -> 98 | M13: =RANK(I13,$I$4:$I$28) -> 4 | N13: =ROUND(I13,0) -> 69
A14: RITU | B14: 58 | C14: 69 | D14: 61 | E14: 73 | F14: 48 | G14: 76 | H14: =SUM(B14:G14) -> 385 | I14: =AVERAGE(B14:G14) -> 64.166667 | J14: =IF(I14>75,"A","B") -> B | K14: =MIN(B14:G14) -> 48 | L14: =MAX(B14:G14) -> 76 | M14: =RANK(I14,$I$4:$I$28) -> 10 | N14: =ROUND(I14,0) -> 64
A15: SAVITA | B15: 47 | C15: 98 | D15: 63 | E15: 35 | F15: 78 | G15: 75 | H15: =SUM(B15:G15) -> 396 | I15: =AVERAGE(B15:G15) -> 66 | J15: =IF(I15>75,"A","B") -> B | K15: =MIN(B15:G15) -> 35 | L15: =MAX(B15:G15) -> 98 | M15: =RANK(I15,$I$4:$I$28) -> 7 | N15: =ROUND(I15,0) -> 66
... A28: GOLU | B28: 45 | C28: 98 | D28: 48 | E28: 38 | F28: 60 | G28: 48 | H28: =SUM(B28:G28) -> 337 | I28: =AVERAGE(B28:G28) -> 56.166667 | J28: =IF(I28>75,"A","B") -> B | K28: =MIN(B28:G28) -> 38 | L28: =MAX(B28:G28) -> 98 | M28: =RANK(I28,$I$4:$I$28) -> 14 | N28: =ROUND(I28,0) -> 56

Sheet STUDENT LIST
A1: STUDENTS list
A4: STUDENTS NAME | B4: roll no. | C4: ENGLISH | D4: HINDI | E4: MATH | F4: SCINECE | G4: TOTAL | H4: PERCENTAGE | I4: RESULT | J4: MIN | K4: MAX | L4: RANK | M4: GRADE
A5: ANKIT | B5: 101 | C5: 35 | D5: 74 | E5: 73 | F5: 98 | G5: =SUM(C5:F5) -> 280 | H5: =AVERAGE(C5:F5) -> 70 | I5: =IF(H5>33,"PASS","FAIL") -> PASS | J5: =MIN(C5:F5) -> 35 | K5: =MAX(C5:F5) -> 98 | L5: =_xlfn.RANK.AVG(H5,$H$5:$H$20) -> 3 | M5: =IF(H5>75,"A",IF(H5>60,"B",IF(H5>45,"C",IF(H5>33,"D",IF(H5<33,"FAIL"))))) -> B
A6: SURAJ | B6: 102 | C6: 91 | D6: 67 | E6: 78 | F6: 54 | G6: =SUM(C6:F6) -> 290 | H6: =AVERAGE(C6:F6) -> 72.5 | I6: =IF(H6>33,"PASS","FAIL") -> PASS | J6: =MIN(C6:F6) -> 54 | K6: =MAX(C6:F6) -> 91 | L6: =_xlfn.RANK.AVG(H6,$H$5:$H$20) -> 2 | M6: =IF(H6>75,"A",IF(H6>60,"B",IF(H6>45,"C",IF(H6>33,"D",IF(H6<33,"FAIL"))))) -> B
A7: NARESH | B7: 103 | C7: 76 | D7: 68 | E7: 67 | F7: 83 | G7: =SUM(C7:F7) -> 294 | H7: =AVERAGE(C7:F7) -> 73.5 | I7: =IF(H7>33,"PASS","FAIL") -> PASS | J7: =MIN(C7:F7) -> 67 | K7: =MAX(C7:F7) -> 83 | L7: =_xlfn.RANK.AVG(H7,$H$5:$H$20) -> 1 | M7: =IF(H7>75,"A",IF(H7>60,"B",IF(H7>45,"C",IF(H7>33,"D",IF(H7<33,"FAIL"))))) -> B
A8: NARAAYAN | B8: 104 | C8: 96 | D8: 83 | E8: 22 | F8: 74 | G8: =SUM(C8:F8) -> 275 | H8: =AVERAGE(C8:F8) -> 68.75 | I8: =IF(H8>33,"PASS","FAIL") -> PASS | J8: =MIN(C8:F8) -> 22 | K8: =MAX(C8:F8) -> 96 | L8: =_xlfn.RANK.AVG(H8,$H$5:$H$20) -> 4 | M8: =IF(H8>75,"A",IF(H8>60,"B",IF(H8>45,"C",IF(H8>33,"D",IF(H8<33,"FAIL"))))) -> B
A9: PANKAJ | B9: 105 | C9: 64 | D9: 13 | E9: 72 | F9: 49 | G9: =SUM(C9:F9) -> 198 | H9: =AVERAGE(C9:F9) -> 49.5 | I9: =IF(H9>33,"PASS","FAIL") -> PASS | J9: =MIN(C9:F9) -> 13 | K9: =MAX(C9:F9) -> 72 | L9: =_xlfn.RANK.AVG(H9,$H$5:$H$20) -> 11 | M9: =IF(H9>75,"A",IF(H9>60,"B",IF(H9>45,"C",IF(H9>33,"D",IF(H9<33,"FAIL"))))) -> C
A10: SASHTRI | B10: 106 | C10: 89 | D10: 67 | E10: 60 | F10: 16 | G10: =SUM(C10:F10) -> 232 | H10: =AVERAGE(C10:F10) -> 58 | I10: =IF(H10>33,"PASS","FAIL") -> PASS | J10: =MIN(C10:F10) -> 16 | K10: =MAX(C10:F10) -> 89 | L10: =_xlfn.RANK.AVG(H10,$H$5:$H$20) -> 7 | M10: =IF(H10>75,"A",IF(H10>60,"B",IF(H10>45,"C",IF(H10>33,"D",IF(H10<33,"FAIL"))))) -> C
A11: KANHAIYA | B11: 107 | C11: 48 | D11: 89 | E11: 100 | F11: 28 | G11: =SUM(C11:F11) -> 265 | H11: =AVERAGE(C11:F11) -> 66.25 | I11: =IF(H11>33,"PASS","FAIL") -> PASS | J11: =MIN(C11:F11) -> 28 | K11: =MAX(C11:F11) -> 100 | L11: =_xlfn.RANK.AVG(H11,$H$5:$H$20) -> 5 | M11: =IF(H11>75,"A",IF(H11>60,"B",IF(H11>45,"C",IF(H11>33,"D",IF(H11<33,"FAIL"))))) -> B
A12: ANUJ | B12: 108 | C12: 29 | D12: 68 | E12: 15 | F12: 15 | G12: =SUM(C12:F12) -> 127 | H12: =AVERAGE(C12:F12) -> 31.75 | I12: =IF(H12>33,"PASS","FAIL") -> FAIL | J12: =MIN(C12:F12) -> 15 | K12: =MAX(C12:F12) -> 68 | L12: =_xlfn.RANK.AVG(H12,$H$5:$H$20) -> 15 | M12: =IF(H12>75,"A",IF(H12>60,"B",IF(H12>45,"C",IF(H12>33,"D",IF(H12<33,"FAIL"))))) -> FAIL
A13: RIJUL | B13: 109 | C13: 28 | D13: 51 | E13: 34 | F13: 45 | G13: =SUM(C13:F13) -> 158 | H13: =AVERAGE(C13:F13) -> 39.5 | I13: =IF(H13>33,"PASS","FAIL") -> PASS | J13: =MIN(C13:F13) -> 28 | K13: =MAX(C13:F13) -> 51 | L13: =_xlfn.RANK.AVG(H13,$H$5:$H$20) -> 14 | M13: =IF(H13>75,"A",IF(H13>60,"B",IF(H13>45,"C",IF(H13>33,"D",IF(H13<33,"FAIL"))))) -> D
A14: KARTIK | B14: 110 | C14: 80 | D14: 30 | E14: 69 | F14: 17 | G14: =SUM(C14:F14) -> 196 | H14: =AVERAGE(C14:F14) -> 49 | I14: =IF(H14>33,"PASS","FAIL") -> PASS | J14: =MIN(C14:F14) -> 17 | K14: =MAX(C14:F14) -> 80 | L14: =_xlfn.RANK.AVG(H14,$H$5:$H$20) -> 12 | M14: =IF(H14>75,"A",IF(H14>60,"B",IF(H14>45,"C",IF(H14>33,"D",IF(H14<33,"FAIL"))))) -> C
A15: SNEHA | B15: 111 | C15: 29 | D15: 30 | E15: 23 | F15: 37 | G15: =SUM(C15:F15) -> 119 | H15: =AVERAGE(C15:F15) -> 29.75 | I15: =IF(H15>33,"PASS","FAIL") -> FAIL | J15: =MIN(C15:F15) -> 23 | K15: =MAX(C15:F15) -> 37 | L15: =_xlfn.RANK.AVG(H15,$H$5:$H$20) -> 16 | M15: =IF(H15>75,"A",IF(H15>60,"B",IF(H15>45,"C",IF(H15>33,"D",IF(H15<33,"FAIL"))))) -> FAIL
A16: PANKAJ | B16: 112 | C16: 57 | D16: 75 | E16: 61 | F16: 52 | G16: =SUM(C16:F16) -> 245 | H16: =AVERAGE(C16:F16) -> 61.25 | I16: =IF(H16>33,"PASS","FAIL") -> PASS | J16: =MIN(C16:F16) -> 52 | K16: =MAX(C16:F16) -> 75 | L16: =_xlfn.RANK.AVG(H16,$H$5:$H$20) -> 6 | M16: =IF(H16>75,"A",IF(H16>60,"B",IF(H16>45,"C",IF(H16>33,"D",IF(H16<33,"FAIL"))))) -> B
... A20: AMAN | B20: 116 | C20: 58 | D20: 41 | E20: 25 | F20: 57 | G20: =SUM(C20:F20) -> 181 | H20: =AVERAGE(C20:F20) -> 45.25 | I20: =IF(H20>33,"PASS","FAIL") -> PASS | J20: =MIN(C20:F20) -> 25 | K20: =MAX(C20:F20) -> 58 | L20: =_xlfn.RANK.AVG(H20,$H$5:$H$20) -> 13 | M20: =IF(H20>75,"A",IF(H20>60,"B",IF(H20>45,"C",IF(H20>33,"D",IF(H20<33,"FAIL"))))) -> C

Sheet PARETOS CHART
A1: PARETOS CHART
A3: EMP NAME | B3: SALARY | C3: DA | D3: PERCENTAGE
A4: ROHAN | B4: 45000 | C4: =B4*25/100 -> 11250 | D4: =C4/B4*100 -> 25 | J4: ]
A5: SOHAN | B5: 12300 | C5: =B5*25/100 -> 3075 | D5: =C5/B5*100 -> 25
A6: KARAN | B6: 89000 | C6: =B6*25/100 -> 22250 | D6: =C6/B6*100 -> 25
A7: KAVITA | B7: 12400 | C7: =B7*25/100 -> 3100 | D7: =C7/B7*100 -> 25
A8: DEEPAK | B8: 56000 | C8: =B8*25/100 -> 14000 | D8: =C8/B8*100 -> 25
A9: DEEPIKA | B9: 23000 | C9: =B9*25/100 -> 5750 | D9: =C9/B9*100 -> 25
A10: LALITA | B10: 45000 | C10: =B10*25/100 -> 11250 | D10: =C10/B10*100 -> 25
A11: GAGAN | B11: 78000 | C11: =B11*25/100 -> 19500 | D11: =C11/B11*100 -> 25
A12: MANISH | B12: 23000 | C12: =B12*25/100 -> 5750 | D12: =C12/B12*100 -> 25
A13: RIYA | B13: 12000 | C13: =B13*25/100 -> 3000 | D13: =C13/B13*100 -> 25
A14: RITU | B14: 56000 | C14: =B14*25/100 -> 14000 | D14: =C14/B14*100 -> 25
A15: SAVITA | B15: 12000 | C15: =B15*25/100 -> 3000 | D15: =C15/B15*100 -> 25
A16: kunal | B16: 82787 | C16: =B16*25/100 -> 20696.75 | D16: =C16/B16*100 -> 25
... A30: VIKAS | B30: 79327 | C30: =B30*25/100 -> 19831.75 | D30: =C30/B30*100 -> 25

Sheet CAHRTS
A1: CHARTS
A5: MONTH | B5: TARGET | C5: SALES
A6: JAN | B6: 592 | C6: 1162
A7: FEB | B7: 630 | C7: 4036
A8: MAR | B8: 527 | C8: 4215
A9: APR | B9: 545 | C9: 5334
A10: MAY | B10: 582 | C10: 6048
A11: JUN | B11: 476 | C11: 1149
A12: JUL | B12: 458 | C12: 6069
A13: AUG | B13: 448 | C13: 5488
A14: SEP | B14: 686 | C14: 5980
A15: OCT | B15: 641 | C15: 5084
A16: NOV | B16: 696 | C16: 1373
A17: DEC | B17: 474 | C17: 1487
... A22: MAY | B22: 613 | C22: 1235

Sheet SPEEDOMETER
A1: SPEEDOMETER
A3: speedometer | F3: pointer
A5: start | B5: 0 | F5: value | G5: 120
A6: initial | B6: 15 | F6: pointer | G6: 12
A7: middle | B7: 45 | F7: ender | G7: 360
A8: end | B8: 40
A9: max | B9: 100

Sheet IF FUNCTION
A1: IF FUCNTION
A3: ITEMS NAME | B3: QTY | C3: RATE | D3: TOTAL | E3: PENDRIVE INCREASE BY 60 | F3: COMPUTER DECREASE BY 70 | G3: NEW RATE | H3: TOTAL SALES WITH NEW RATE
A4: shirts | B4: 12 | C4: 450 | D4: =C4*B4 -> 5400 | E4: =IF(A4="pen drive",C4+60,C4) -> 450 | F4: =IF(A4="computer",C4-70,E4) -> 450 | G4: =F4 -> 450 | H4: =G4*B4 -> 5400
A5: t-shirts | B5: 56 | C5: 560 | D5: =C5*B5 -> 31360 | E5: =IF(A5="pen drive",C5+60,C5) -> 560 | F5: =IF(A5="computer",C5-70,E5) -> 560 | G5: =F5 -> 560 | H5: =G5*B5 -> 31360
A6: suits | B6: 25 | C6: 230 | D6: =C6*B6 -> 5750 | E6: =IF(A6="pen drive",C6+60,C6) -> 230 | F6: =IF(A6="computer",C6-70,E6) -> 230 | G6: =F6 -> 230 | H6: =G6*B6 -> 5750
A7: jeans | B7: 98 | C7: 120 | D7: =C7*B7 -> 11760 | E7: =IF(A7="pen drive",C7+60,C7) -> 120 | F7: =IF(A7="computer",C7-70,E7) -> 120 | G7: =F7 -> 120 | H7: =G7*B7 -> 11760
A8: kurta | B8: 32 | C8: 450 | D8: =C8*B8 -> 14400 | E8: =IF(A8="pen drive",C8+60,C8) -> 450 | F8: =IF(A8="computer",C8-70,E8) -> 450 | G8: =F8 -> 450 | H8: =G8*B8 -> 14400
A9: jacket | B9: 65 | C9: 890 | D9: =C9*B9 -> 57850 | E9: =IF(A9="pen drive",C9+60,C9) -> 890 | F9: =IF(A9="computer",C9-70,E9) -> 890 | G9: =F9 -> 890 | H9: =G9*B9 -> 57850
A10: mouse | B10: 26 | C10: 120 | D10: =C10*B10 -> 3120 | E10: =IF(A10="pen drive",C10+60,C10) -> 120 | F10: =IF(A10="computer",C10-70,E10) -> 120 | G10: =F10 -> 120 | H10: =G10*B10 -> 3120
A11: key board | B11: 45 | C11: 230 | D11: =C11*B11 -> 10350 | E11: =IF(A11="pen drive",C11+60,C11) -> 230 | F11: =IF(A11="computer",C11-70,E11) -> 230 | G11: =F11 -> 230 | H11: =G11*B11 -> 10350
A12: pen drive | B12: 36 | C12: 560 | D12: =C12*B12 -> 20160 | E12: =IF(A12="pen drive",C12+60,C12) -> 620 | F12: =IF(A12="computer",C12-70,E12) -> 620 | G12: =F12 -> 620 | H12: =G12*B12 -> 22320
A13: computer | B13: 36 | C13: 1270 | D13: =C13*B13 -> 45720 | E13: =IF(A13="pen drive",C13+60,C13) -> 1270 | F13: =IF(A13="computer",C13-70,E13) -> 1200 | G13: =F13 -> 1200 | H13: =G13*B13 -> 43200
A14: hard disk | B14: 20 | C14: 890 | D14: =C14*B14 -> 17800 | E14: =IF(A14="pen drive",C14+60,C14) -> 890 | F14: =IF(A14="computer",C14-70,E14) -> 890 | G14: =F14 -> 890 | H14: =G14*B14 -> 17800
A15: C.P.U | B15: 45 | C15: 2300 | D15: =C15*B15 -> 103500 | E15: =IF(A15="pen drive",C15+60,C15) -> 2300 | F15: =IF(A15="computer",C15-70,E15) -> 2300 | G15: =F15 -> 2300 | H15: =G15*B15 -> 103500
... A27: sewing machine | B27: 83 | C27: 902 | D27: =C27*B27 -> 74866 | E27: =IF(A27="pen drive",C27+60,C27) -> 902 | F27: =IF(A27="computer",C27-70,E27) -> 902 | G27: =F27 -> 902 | H27: =G27*B27 -> 74866

Sheet IF FUNCITON 2
A1: IF FUCNITON
A3: month | B3: asd-01 | C3: asd-02 | D3: asd-04 | E3: asd-04 | F3: total sales
A4: jan | B4: 456 | C4: 485 | D4: 656 | E4: 565 | F4: =SUM(B4:E4) -> 2162
A5: feb | B5: 231 | C5: 565 | D5: 632 | E5: 656 | F5: =SUM(B5:E5) -> 2084
A6: mar | B6: 654 | C6: 452 | D6: 584 | E6: 323 | F6: =SUM(B6:E6) -> 2013
A7: apr | B7: 568 | C7: 895 | D7: 698 | E7: 563 | F7: =SUM(B7:E7) -> 2724
A8: may | B8: 232 | C8: 656 | D8: 254 | E8: 454 | F8: =SUM(B8:E8) -> 1596
A9: jun | B9: 124 | C9: 452 | D9: 256 | E9: 325 | F9: =SUM(B9:E9) -> 1157
A10: jul | B10: 665 | C10: 625 | D10: 695 | E10: 454 | F10: =SUM(B10:E10) -> 2439
A11: aug | B11: 987 | C11: 897 | D11: 647 | E11: 256 | F11: =SUM(B11:E11) -> 2787
A12: sep | B12: 654 | C12: 457 | D12: 214 | E12: 452 | F12: =SUM(B12:E12) -> 1777
A13: oct | B13: 698 | C13: 565 | D13: 321 | E13: 563 | F13: =SUM(B13:E13) -> 2147
A14: nov | B14: 235 | C14: 656 | D14: 365 | E14: 452 | F14: =SUM(B14:E14) -> 1708
A15: dec | B15: 565 | C15: 232 | D15: 256 | E15: 232 | F15: =SUM(B15:E15) -> 1285
... A25: oct | B25: 698 | C25: 565 | D25: 321 | E25: 563 | F25: =SUM(B25:E25) -> 2147

Sheet SALES REPORT
A1: SALES REPORT
A3: Emp Name | B3: jan | C3: feb | D3: mar | E3: apr | F3: may | G3: jun | H3: jul | I3: aug | J3: sep | K3: oct | L3: nov | M3: dec | N3: total
A4: hari | B4: 46545 | C4: 12547 | D4: 98547 | E4: 56844 | F4: 56145 | G4: 36568 | H4: 23565 | I4: 56145 | J4: 36568 | K4: 23565 | L4: 58474 | M4: 23553 | N4: =SUM(B4:M4) -> 529066
A5: mohan | B5: 23000 | C5: 65987 | D5: 54568 | E5: 36568 | F5: 26541 | G5: 32154 | H5: 36564 | I5: 26541 | J5: 32154 | K5: 36564 | L5: 36521 | M5: 23541 | N5: =SUM(B5:M5) -> 430703
A6: john | B6: 56000 | C6: 56145 | D6: 36568 | E6: 23565 | F6: 58474 | G6: 23553 | H6: 69584 | I6: 58474 | J6: 23553 | K6: 69584 | L6: 25641 | M6: 32654 | N6: =SUM(B6:M6) -> 533795
A7: gagan | B7: 23450 | C7: 26541 | D7: 32154 | E7: 36564 | F7: 36521 | G7: 23541 | H7: 36524 | I7: 36521 | J7: 23541 | K7: 36524 | L7: 12543 | M7: 36521 | N7: =SUM(B7:M7) -> 360945
A8: deepak | B8: 69580 | C8: 58474 | D8: 23553 | E8: 69584 | F8: 25641 | G8: 32654 | H8: 36547 | I8: 25641 | J8: 32654 | K8: 36547 | L8: 32214 | M8: 25641 | N8: =SUM(B8:M8) -> 468730
A9: lalita | B9: 12543 | C9: 36521 | D9: 23541 | E9: 36524 | F9: 12543 | G9: 36521 | H9: 23541 | I9: 56478 | J9: 21566 | K9: 98564 | L9: 23001 | M9: 56478 | N9: =SUM(B9:M9) -> 437821
A10: riya | B10: 32214 | C10: 25641 | D10: 32654 | E10: 36547 | F10: 32214 | G10: 25641 | H10: 32654 | I10: 66958 | J10: 36594 | K10: 69557 | L10: 56412 | M10: 66958 | N10: =SUM(B10:M10) -> 514044
A11: siya | B11: 23001 | C11: 56478 | D11: 21566 | E11: 98564 | F11: 23001 | G11: 56478 | H11: 21566 | I11: 36524 | J11: 23564 | K11: 25456 | L11: 23145 | M11: 36524 | N11: =SUM(B11:M11) -> 445867
A12: savita | B12: 56412 | C12: 66958 | D12: 36594 | E12: 69557 | F12: 56412 | G12: 66958 | H12: 36594 | I12: 36524 | J12: 23564 | K12: 25456 | L12: 23145 | M12: 36524 | N12: =SUM(B12:M12) -> 534698
A13: sarita | B13: 23145 | C13: 36524 | D13: 23564 | E13: 25456 | F13: 23145 | G13: 36524 | H13: 23564 | I13: 25641 | J13: 32124 | K13: 26547 | L13: 56984 | M13: 25641 | N13: =SUM(B13:M13) -> 358859
A14: yash | B14: 56984 | C14: 25641 | D14: 32124 | E14: 26547 | F14: 56984 | G14: 25641 | H14: 32124 | I14: 56886 | J14: 36445 | K14: 36586 | L14: 46545 | M14: 12547 | N14: =SUM(B14:M14) -> 445054
A15: mohini | B15: 36587 | C15: 56886 | D15: 36445 | E15: 36586 | F15: 46545 | G15: 12547 | H15: 98547 | I15: 46545 | J15: 12547 | K15: 98547 | L15: 56145 | M15: 36568 | N15: =SUM(B15:M15) -> 574495
... A18: john | B18: 56000 | C18: 56145 | D18: 36568 | E18: 23565 | F18: 58474 | G18: 23553 | H18: 69584 | I18: 58474 | J18: 23553 | K18: 69584 | L18: 25641 | M18: 32654 | N18: =SUM(B18:M18) -> 533795

Sheet DEPRECIATION
A1: CALCULATE DEPRECIATION
A4: ITEM NAME | B4: COST | C4: ESTIMATED | D4: YEAR OF USEFUL
A5: computer | B5: 30000 | C5: 7500 | D5: 10
A6: heater | B6: 56000 | C6: 2300 | D6: 5
A7: cooler | B7: 120000 | C7: 5000 | D7: 12
A8: hard disk | B8: 230000 | C8: 1500 | D8: 23
A9: lap top | B9: 450000 | C9: 4500 | D9: 15
A10: iphone | B10: 890000 | C10: 1200 | D10: 50
A11: room cleaning | B11: 20000 | C11: 500 | D11: 20
A12: food | B12: 56000 | C12: 230 | D12: 42
A13: mouse | B13: 750000 | C13: 5600 | D13: 10
A14: key board | B14: 450000 | C14: 5200 | D14: 50
A15: suits | B15: 230000 | C15: 9600 | D15: 25
A16: scooter | B16: 450000 | C16: 2300 | D16: 14
... A25: tyres | B25: 230000 | C25: 1500 | D25: 23

Sheet FINACNICAL 
A1: FINANCIAL FUNCITON
A3: Annual Interest Rate | B3: Period | C3: No of Year in the investment | D3: loan
A4: 0.1 | B4: 2 | C4: 3 | D4: 800000
A5: 0.12 | B5: 2 | C5: 2 | D5: 1200000
A6: 0.08 | B6: 5 | C6: 1 | D6: 560000
A7: 0.09 | B7: 3 | C7: 4 | D7: 420000
A8: 0.15 | B8: 6 | C8: 3 | D8: 230000
A9: 0.22 | B9: 4 | C9: 2 | D9: 120000
A10: 0.2 | B10: 3 | C10: 4 | D10: 520000
A11: 0.02 | B11: 2 | C11: 1 | D11: 320000
A12: 0.05 | B12: 1 | C12: 3 | D12: 140000
A13: 0.07 | B13: 5 | C13: 4 | D13: 520000
A14: 0.25 | B14: 6 | C14: 2 | D14: 350000
A15: 0.075 | B15: 2 | C15: 3 | D15: 253000
... A23: 0.08 | B23: 5 | C23: 1 | D23: 560000

Sheet VLOOKUP
A1: VLOOKUP
G2: ARRAY TABLE 1
A3: product ID | B3: product desc | C3: sales desc | D3: calender day | E3: month year | G3: PRODUCT ID | H3: PRODUCT DESC
A4: pos01 | B4: =VLOOKUP(A4,G4:$H$10,2,FALSE) -> NOTE BOOK SPEEDY I | C4: 7389 | D4: 39268 | E4: =VLOOKUP(D4,$G$16:$H$25,2,FALSE) -> 39264 | G4: POS01 | H4: NOTE BOOK SPEEDY I
A5: pos02 | B5: =VLOOKUP(A5,G5:$H$10,2,FALSE) -> NOTE BOOK SPEEDY II | C5: 2654 | D5: 39268 | E5: =VLOOKUP(D5,$G$16:$H$25,2,FALSE) -> 39264 | G5: POS02 | H5: NOTE BOOK SPEEDY II
A6: pos01 | B6: =VLOOKUP(A6,G4:$H$10,2,FALSE) -> NOTE BOOK SPEEDY I | C6: 1214 | D6: 39269 | E6: =VLOOKUP(D6,$G$16:$H$25,2,FALSE) -> 39264 | G6: POS03 | H6: PC THINK BOX
A7: pos03 | B7: =VLOOKUP(A7,G5:$H$10,2,FALSE) -> PC THINK BOX | C7: 6665 | D7: 39269 | E7: =VLOOKUP(D7,$G$16:$H$25,2,FALSE) -> 39264 | G7: POS04 | H7: USB ADAPTOR
A8: pos05 | B8: =VLOOKUP(A8,G6:$H$10,2,FALSE) -> IPHONES PXL | C8: 1425 | D8: 39281 | E8: =VLOOKUP(D8,$G$16:$H$27,2,FALSE) -> 39395 | G8: POS05 | H8: IPHONES PXL
A9: pos04 | B9: =VLOOKUP(A9,G7:$H$10,2,FALSE) -> USB ADAPTOR | C9: 2124 | D9: 39301 | E9: =VLOOKUP(D9,$G$16:$H$27,2,FALSE) -> 39295 | G9: POS06 | H9: CAMERA CONNECTOR
A10: pos07 | B10: =VLOOKUP(A10,G8:$H$10,2,FALSE) -> SAMSUNG CHARGER | C10: 6587 | D10: 39306 | E10: =VLOOKUP(D10,$G$16:$H$27,2,FALSE) -> 39295 | G10: POS07 | H10: SAMSUNG CHARGER
A11: pos01 | B11: =VLOOKUP(A11,$G$4:$H$10,2,FALSE) -> NOTE BOOK SPEEDY I | C11: 6958 | D11: 39316 | E11: =VLOOKUP(D11,$G$16:$H$27,2,FALSE) -> 49485
A12: pos02 | B12: =VLOOKUP(A12,$G$4:$H$10,2,FALSE) -> NOTE BOOK SPEEDY II | C12: 3652 | D12: 39316 | E12: =VLOOKUP(D12,$G$16:$H$27,2,FALSE) -> 49485
A13: pos01 | B13: =VLOOKUP(A13,$G$4:$H$10,2,FALSE) -> NOTE BOOK SPEEDY I | C13: 1215 | D13: 39301 | E13: =VLOOKUP(D13,$G$16:$H$27,2,FALSE) -> 39295
A14: pos03 | B14: =VLOOKUP(A14,$G$4:$H$10,2,FALSE) -> PC THINK BOX | C14: 5847 | D14: 39269 | E14: =VLOOKUP(D14,$G$16:$H$27,2,FALSE) -> 39264 | G14: ARRAY TABLE 2
A15: pos05 | B15: =VLOOKUP(A15,$G$4:$H$10,2,FALSE) -> IPHONES PXL | C15: 2687 | D15: 39269 | E15: =VLOOKUP(D15,$G$16:$H$27,2,FALSE) -> 39264 | G15: DATE | H15: MON-YEAR
A16: pos04 | B16: =VLOOKUP(A16,$G$4:$H$10,2,FALSE) -> USB ADAPTOR | C16: 2013 | D16: 39281 | E16: =VLOOKUP(D16,$G$16:$H$27,2,FALSE) -> 39395 | G16: 39268 | H16: 39264
A17: pos07 | B17: =VLOOKUP(A17,$G$4:$H$10,2,FALSE) -> SAMSUNG CHARGER | C17: 6547 | D17: 39301 | E17: =VLOOKUP(D17,$G$16:$H$27,2,FALSE) -> 39295 | G17: 39269 | H17: 39264
A18: pos01 | B18: =VLOOKUP(A18,$G$4:$H$10,2,FALSE) -> NOTE BOOK SPEEDY I | C18: 2013 | D18: 39306 | E18: =VLOOKUP(D18,$G$16:$H$27,2,FALSE) -> 39295 | G18: 39274 | H18: 39264
A19: pos02 | B19: =VLOOKUP(A19,$G$4:$H$10,2,FALSE) -> NOTE BOOK SPEEDY II | C19: 6547 | D19: 39316 | E19: =VLOOKUP(D19,$G$16:$H$27,2,FALSE) -> 49485 | G19: 39300 | H19: 39295
A20: pos01 | B20: =VLOOKUP(A20,$G$4:$H$10,2,FALSE) -> NOTE BOOK SPEEDY I | C20: 5689 | D20: 39316 | E20: =VLOOKUP(D20,$G$16:$H$27,2,FALSE) -> 49485 | G20: 39301 | H20: 39295
A21: pos03 | B21: =VLOOKUP(A21,$G$4:$H$10,2,FALSE) -> PC THINK BOX | C21: 6561 | D21: 39281 | E21: =VLOOKUP(D21,$G$16:$H$27,2,FALSE) -> 39395 | G21: 39306 | H21: 39295
A22: pos01 | B22: =VLOOKUP(A22,$G$4:$H$10,2,FALSE) -> NOTE BOOK SPEEDY I | C22: 6665 | D22: 39268 | E22: =VLOOKUP(D22,$G$16:$H$27,2,FALSE) -> 39264 | G22: 39300 | H22: 39295
A23: pos03 | B23: =VLOOKUP(A23,$G$4:$H$10,2,FALSE) -> PC THINK BOX | C23: 1425 | D23: 39281 | E23: =VLOOKUP(D23,$G$16:$H$27,2,FALSE) -> 39395 | G23: 39301 | H23: 39295
A24: pos05 | B24: =VLOOKUP(A24,$G$4:$H$10,2,FALSE) -> IPHONES PXL | C24: 2124 | D24: 39306 | E24: =VLOOKUP(D24,$G$16:$H$27,2,FALSE) -> 39295 | G24: 39306 | H24: 39295
A25: pos04 | B25: =VLOOKUP(A25,$G$4:$H$10,2,FALSE) -> USB ADAPTOR | C25: 6587 | D25: 39316 | E25: =VLOOKUP(D25,$G$16:$H$27,2,FALSE) -> 49485 | G25: 39309 | H25: 39295
G26: 39281 | H26: 39395
G27: 39316 | H27: 49485

Sheet HLOOK UP
D1: HLOOK UP
A6: product ID | B6: pos01 | C6: pos02 | D6: pos01 | E6: pos03 | F6: pos05 | G6: pos04 | H6: pos07 | I6: pos01 | J6: pos02 | K6: pos01 | L6: pos03 | M6: pos05 | N6: pos04 | O6: pos07 | P6: pos01 | Q6: pos02 | R6: pos01 | S6: pos03 | T6: pos01 | U6: pos03 | V6: pos05 | W6: pos04
A7: product desc | B7: =HLOOKUP(B6,$D$14:$J$15,2,FALSE) -> NOTE BOOK SPEEDY I | C7: =HLOOKUP(C6,$D$14:$J$15,2,FALSE) -> NOTE BOOK SPEEDY II | D7: =HLOOKUP(D6,$D$14:$J$15,2,FALSE) -> NOTE BOOK SPEEDY I | E7: =HLOOKUP(E6,$D$14:$J$15,2,FALSE) -> PC THINK BOX | F7: =HLOOKUP(F6,$D$14:$J$15,2,FALSE) -> IPHONES PXL | G7: =HLOOKUP(G6,$D$14:$J$15,2,FALSE) -> USB ADAPTOR | H7: =HLOOKUP(H6,$D$14:$J$15,2,FALSE) -> SAMSUNG CHARGER | I7: =HLOOKUP(I6,$D$14:$J$15,2,FALSE) -> NOTE BOOK SPEEDY I | ... W7: =HLOOKUP(W6,$D$14:$J$15,2,FALSE) -> USB ADAPTOR
A8: sales desc | B8: 7389 | C8: 2654 | D8: 1214 | E8: 6665 | F8: 1425 | G8: 2124 | H8: 6587 | I8: 6958 | J8: 3652 | K8: 1215 | L8: 5847 | M8: 2687 | N8: 2013 | O8: 6547 | P8: 2013 | Q8: 6547 | R8: 5689 | S8: 6561 | T8: 6665 | U8: 1425 | V8: 2124 | W8: 6587
A9: calender day | B9: 39268 | C9: 39268 | D9: 39269 | E9: 39269 | F9: 39281 | G9: 39301 | H9: 39306 | I9: 39316 | J9: 39316 | K9: 39301 | L9: 39269 | M9: 39269 | N9: 39281 | O9: 39301 | P9: 39306 | Q9: 39316 | R9: 39316 | S9: 39281 | T9: 39268 | U9: 39281 | V9: 39306 | W9: 39316
A10: month year | B10: =HLOOKUP('HLOOK UP'!B9,'HLOOK UP'!$E$19:$P$20,2,FALSE) -> 39264 | C10: =HLOOKUP('HLOOK UP'!C9,'HLOOK UP'!$E$19:$P$20,2,FALSE) -> 39264 | D10: =HLOOKUP('HLOOK UP'!D9,'HLOOK UP'!$E$19:$P$20,2,FALSE) -> 39264 | E10: =HLOOKUP('HLOOK UP'!E9,'HLOOK UP'!$E$19:$P$20,2,FALSE) -> 39264 | F10: =HLOOKUP('HLOOK UP'!F9,'HLOOK UP'!$E$19:$P$20,2,FALSE) -> 39395 | G10: =HLOOKUP('HLOOK UP'!G9,'HLOOK UP'!$E$19:$P$20,2,FALSE) -> 39295 | H10: =HLOOKUP('HLOOK UP'!H9,'HLOOK UP'!$E$19:$P$20,2,FALSE) -> 39295 | I10: =HLOOKUP('HLOOK UP'!I9,'HLOOK UP'!$E$19:$P$20,2,FALSE) -> 49485 | ... W10: =HLOOKUP('HLOOK UP'!W9,'HLOOK UP'!$E$19:$P$20,2,FALSE) -> 49485
A14: ARRAY TABLE 1 | C14: PRODUCT ID | D14: POS01 | E14: POS02 | F14: POS03 | G14: POS04 | H14: POS05 | I14: POS06 | J14: POS07
C15: PRODUCT DESC | D15: NOTE BOOK SPEEDY I | E15: NOTE BOOK SPEEDY II | F15: PC THINK BOX | G15: USB ADAPTOR | H15: IPHONES PXL | I15: CAMERA CONNECTOR | J15: SAMSUNG CHARGER
A19: ARRAY TABLE 2 | D19: DATE | E19: 39268 | F19: 39269 | G19: 39274 | H19: 39300 | I19: 39301 | J19: 39306 | K19: 39300 | L19: 39301 | M19: 39306 | N19: 39309 | O19: 39281 | P19: 39316
D20: MON-YEAR | E20: 39264 | F20: 39264 | G20: 39264 | H20: 39295 | I20: 39295 | J20: 39295 | K20: 39295 | L20: 39295 | M20: 39295 | N20: 39295 | O20: 39395 | P20: 49485
B27: HLOOKUP

Sheet FILTER
A1: MONTHLY REPORT
A3: YEAR | B3: JAN | C3: FEB | D3: MAR | E3: APR | F3: MAY | G3: JUN | H3: JUL | I3: AUG | J3: SEP | K3: OCT | L3: NOV | M3: DEC | N3: TOTAL | O3: AVERAGE
A4: 1988 | B4: 31 | C4: 29 | D4: 31 | E4: 30 | F4: 25 | G4: 31 | H4: 25 | I4: 30 | J4: 29 | K4: 31 | L4: 25 | M4: 30 | N4: =SUM(Table13[[#This Row],[JAN]:[DEC]]) -> 347 | O4: =AVERAGE(Table13[[#This Row],[JAN]:[DEC]]) -> 28.916667
A5: 1989 | B5: 31 | C5: 28 | D5: 31 | E5: 30 | F5: 26 | G5: 31 | H5: 26 | I5: 30 | J5: 28 | K5: 31 | L5: 26 | M5: 30 | N5: =SUM(Table13[[#This Row],[JAN]:[DEC]]) -> 348 | O5: =AVERAGE(Table13[[#This Row],[JAN]:[DEC]]) -> 29
A6: 1990 | B6: 31 | C6: 29 | D6: 31 | E6: 30 | F6: 25 | G6: 31 | H6: 25 | I6: 30 | J6: 29 | K6: 31 | L6: 25 | M6: 30 | N6: =SUM(Table13[[#This Row],[JAN]:[DEC]]) -> 347 | O6: =AVERAGE(Table13[[#This Row],[JAN]:[DEC]]) -> 28.916667
A7: 1991 | B7: 31 | C7: 28 | D7: 31 | E7: 30 | F7: 26 | G7: 31 | H7: 26 | I7: 30 | J7: 28 | K7: 31 | L7: 26 | M7: 30 | N7: =SUM(Table13[[#This Row],[JAN]:[DEC]]) -> 348 | O7: =AVERAGE(Table13[[#This Row],[JAN]:[DEC]]) -> 29
A8: 1992 | B8: 31 | C8: 29 | D8: 31 | E8: 30 | F8: 25 | G8: 31 | H8: 25 | I8: 30 | J8: 29 | K8: 31 | L8: 25 | M8: 30 | N8: =SUM(Table13[[#This Row],[JAN]:[DEC]]) -> 347 | O8: =AVERAGE(Table13[[#This Row],[JAN]:[DEC]]) -> 28.916667
A9: 1993 | B9: 31 | C9: 28 | D9: 31 | E9: 30 | F9: 26 | G9: 31 | H9: 26 | I9: 30 | J9: 28 | K9: 31 | L9: 26 | M9: 30 | N9: =SUM(Table13[[#This Row],[JAN]:[DEC]]) -> 348 | O9: =AVERAGE(Table13[[#This Row],[JAN]:[DEC]]) -> 29
A10: 1994 | B10: 31 | C10: 29 | D10: 31 | E10: 30 | F10: 25 | G10: 31 | H10: 25 | I10: 30 | J10: 29 | K10: 31 | L10: 25 | M10: 30 | N10: =SUM(Table13[[#This Row],[JAN]:[DEC]]) -> 347 | O10: =AVERAGE(Table13[[#This Row],[JAN]:[DEC]]) -> 28.916667
A11: 1995 | B11: 31 | C11: 28 | D11: 31 | E11: 30 | F11: 26 | G11: 31 | H11: 26 | I11: 30 | J11: 28 | K11: 31 | L11: 26 | M11: 30 | N11: =SUM(Table13[[#This Row],[JAN]:[DEC]]) -> 348 | O11: =AVERAGE(Table13[[#This Row],[JAN]:[DEC]]) -> 29
A12: 1996 | B12: 31 | C12: 29 | D12: 31 | E12: 30 | F12: 25 | G12: 31 | H12: 25 | I12: 30 | J12: 29 | K12: 31 | L12: 25 | M12: 30 | N12: =SUM(Table13[[#This Row],[JAN]:[DEC]]) -> 347 | O12: =AVERAGE(Table13[[#This Row],[JAN]:[DEC]]) -> 28.916667
A13: 1997 | B13: 31 | C13: 28 | D13: 31 | E13: 30 | F13: 26 | G13: 31 | H13: 26 | I13: 30 | J13: 28 | K13: 31 | L13: 26 | M13: 30 | N13: =SUM(Table13[[#This Row],[JAN]:[DEC]]) -> 348 | O13: =AVERAGE(Table13[[#This Row],[JAN]:[DEC]]) -> 29
A14: 1998 | B14: 31 | C14: 29 | D14: 31 | E14: 30 | F14: 25 | G14: 31 | H14: 25 | I14: 30 | J14: 29 | K14: 31 | L14: 25 | M14: 30 | N14: =SUM(Table13[[#This Row],[JAN]:[DEC]]) -> 347 | O14: =AVERAGE(Table13[[#This Row],[JAN]:[DEC]]) -> 28.916667
A15: 1999 | B15: 31 | C15: 28 | D15: 31 | E15: 30 | F15: 26 | G15: 31 | H15: 26 | I15: 30 | J15: 28 | K15: 31 | L15: 26 | M15: 30 | N15: =SUM(Table13[[#This Row],[JAN]:[DEC]]) -> 348 | O15: =AVERAGE(Table13[[#This Row],[JAN]:[DEC]]) -> 29
... A30: 2014 | B30: 31 | C30: 29 | D30: 31 | E30: 30 | F30: 25 | G30: 31 | H30: 25 | I30: 30 | J30: 29 | K30: 31 | L30: 25 | M30: 30 | N30: =SUM(Table13[[#This Row],[JAN]:[DEC]]) -> 347 | O30: =AVERAGE(Table13[[#This Row],[JAN]:[DEC]]) -> 28.916667

Sheet SUMIF
A1: SUMIF
A3: SALES MAN | B3: ITEM | C3: RATE | D3: SOLID ITEM | E3: TOTAL SALES [Rs.]
A4: SURESH | B4: COMPUTER | C4: 55000 | D4: 7 | E4: =D4*C4 -> 385000
A5: VICKY | B5: COMPUTER | C5: 26500 | D5: 7 | E5: =D5*C5 -> 185500
A6: HERJEET | B6: COMPUTER | C6: 52600 | D6: 34 | E6: =D6*C6 -> 1788400
A7: PRAMOD | B7: COMPUTER | C7: 96100 | D7: 32 | E7: =D7*C7 -> 3075200
A8: AMIT | B8: OVEN | C8: 7500 | D8: 5 | E8: =D8*C8 -> 37500 | H8: TOTAL SALES OF COMPUTER | I8: =SUMIF(B4:B44,B5,E4:E44) -> 14909400
A9: RAJESH | B9: OVEN | C9: 43900 | D9: 5 | E9: =D9*C9 -> 219500 | H9: TOTAL SALES OF OVEN | I9: =SUMIF(B4:B44,B8,E4:E44) -> 5554800
A10: SANDEEP | B10: OVEN | C10: 61300 | D10: 12 | E10: =D10*C10 -> 735600 | H10: TOTA;L SALES OF VCR | I10: =SUMIF(B4:B44,B16,E4:E44) -> 8202400
A11: PRAMOD | B11: REFRIFERATOR | C11: 9100 | D11: 45 | E11: =D11*C11 -> 409500 | H11: TOTAL SALES OF ALL SALESMAN
A12: AMIT | B12: REFRIFERATOR | C12: 78700 | D12: 17 | E12: =D12*C12 -> 1337900
A13: SANDEEP | B13: STEREO | C13: 3500 | D13: 5 | E13: =D13*C13 -> 17500
A14: ARUN | B14: STEREO | C14: 35200 | D14: 27 | E14: =D14*C14 -> 950400
A15: REEMA | B15: VCR | C15: 17800 | D15: 4 | E15: =D15*C15 -> 71200
A16: VIKAS | B16: VCR | C16: 17800 | D16: 8 | E16: =D16*C16 -> 142400
A17: SURESH | B17: VCR | C17: 70000 | D17: 16 | E17: =D17*C17 -> 1120000
A18: REEMA | B18: VCR | C18: 87400 | D18: 31 | E18: =D18*C18 -> 2709400
A19: kunal | B19: COMPUTER | C19: 17800 | D19: 43 | E19: =D19*C19 -> 765400
A20: devender | B20: COMPUTER | C20: 52600 | D20: 45 | E20: =D20*C20 -> 2367000
A21: AKHIL | B21: COMPUTER | C21: 7500 | D21: 12 | E21: =D21*C21 -> 90000
A22: MUKESH | B22: COMPUTER | C22: 61300 | D22: 40 | E22: =D22*C22 -> 2452000
A23: AMIT | B23: OVEN | C23: 9100 | D23: 16 | E23: =D23*C23 -> 145600
... A44: ARUN | B44: STEREO | C44: 87400 | D44: 35 | E44: =D44*C44 -> 3059000

Sheet IF&SUM
A1: SALES REPROT
A3: ITEMS | B3: JAN | C3: FEB | D3: MAR | E3: TOTAL SALES (QTY) | F3: RATE/PIECE | G3: TOTAL SALES (RS) | H3: TARGET | I3: RESULT
A4: CARDIGAN | B4: 234 | C4: 535 | D4: 257 | E4: =SUM(B4:D4) -> 1026 | F4: 347 | G4: =F4*E4 -> 356022 | H4: =IF(G4>$O$6,"ACHIEVED","NOT ACHIEVED") -> NOT ACHIEVED
A5: HALF-PANT | B5: 198 | C5: 56 | D5: 89 | E5: =SUM(B5:D5) -> 343 | F5: 347 | G5: =F5*E5 -> 119021 | H5: =IF(G5>$O$6,"ACHIEVED","NOT ACHIEVED") -> NOT ACHIEVED
A6: JACKETS | B6: 128 | C6: 357 | D6: 341 | E6: =SUM(B6:D6) -> 826 | F6: 562 | G6: =F6*E6 -> 464212 | H6: =IF(G6>$O$6,"ACHIEVED","NOT ACHIEVED") -> NOT ACHIEVED | N6: TARGET | O6: 600000
A7: JEANS-BLAZER | B7: 748 | C7: 235 | D7: 985 | E7: =SUM(B7:D7) -> 1968 | F7: 348 | G7: =F7*E7 -> 684864 | H7: =IF(G7>$O$6,"ACHIEVED","NOT ACHIEVED") -> ACHIEVED
A8: JEANS-JACK | B8: 985 | C8: 456 | D8: 128 | E8: =SUM(B8:D8) -> 1569 | F8: 633 | G8: =F8*E8 -> 993177 | H8: =IF(G8>$O$6,"ACHIEVED","NOT ACHIEVED") -> ACHIEVED | N8: TOTAL NUMBER OF TARGET ACHIEVED | O8: =COUNTIF(H4:H22,H8) -> 7
A9: KURTA PAJAMA | B9: 754 | C9: 454 | D9: 748 | E9: =SUM(B9:D9) -> 1956 | F9: 234 | G9: =F9*E9 -> 457704 | H9: =IF(G9>$O$6,"ACHIEVED","NOT ACHIEVED") -> NOT ACHIEVED
A10: LEE JACKETS | B10: 142 | C10: 467 | D10: 342 | E10: =SUM(B10:D10) -> 951 | F10: 348 | G10: =F10*E10 -> 330948 | H10: =IF(G10>$O$6,"ACHIEVED","NOT ACHIEVED") -> NOT ACHIEVED
A11: LEE JEANS | B11: 532 | C11: 745 | D11: 743 | E11: =SUM(B11:D11) -> 2020 | F11: 633 | G11: =F11*E11 -> 1278660 | H11: =IF(G11>$O$6,"ACHIEVED","NOT ACHIEVED") -> ACHIEVED
A12: PULLOVERS | B12: 145 | C12: 854 | D12: 234 | E12: =SUM(B12:D12) -> 1233 | F12: 345 | G12: =F12*E12 -> 425385 | H12: =IF(G12>$O$6,"ACHIEVED","NOT ACHIEVED") -> NOT ACHIEVED
A13: SHIRTS | B13: 123 | C13: 954 | D13: 254 | E13: =SUM(B13:D13) -> 1331 | F13: 389 | G13: =F13*E13 -> 517759 | H13: =IF(G13>$O$6,"ACHIEVED","NOT ACHIEVED") -> NOT ACHIEVED
A14: SUITES | B14: 342 | C14: 785 | D14: 356 | E14: =SUM(B14:D14) -> 1483 | F14: 563 | G14: =F14*E14 -> 834929 | H14: =IF(G14>$O$6,"ACHIEVED","NOT ACHIEVED") -> ACHIEVED
A15: TROUSERS | B15: 257 | C15: 422 | D15: 754 | E15: =SUM(B15:D15) -> 1433 | F15: 327 | G15: =F15*E15 -> 468591 | H15: =IF(G15>$O$6,"ACHIEVED","NOT ACHIEVED") -> NOT ACHIEVED
A16: T-SHIRTS | B16: 341 | C16: 964 | D16: 978 | E16: =SUM(B16:D16) -> 2283 | F16: 563 | G16: =F16*E16 -> 1285329 | H16: =IF(G16>$O$6,"ACHIEVED","NOT ACHIEVED") -> ACHIEVED
A17: VIP JACKETS | B17: 34 | C17: 23 | D17: 67 | E17: =SUM(B17:D17) -> 124 | F17: 234 | G17: =F17*E17 -> 29016 | H17: =IF(G17>$O$6,"ACHIEVED","NOT ACHIEVED") -> NOT ACHIEVED
A18: VIP SHIRTS | B18: 23 | C18: 45 | D18: 34 | E18: =SUM(B18:D18) -> 102 | F18: 327 | G18: =F18*E18 -> 33354 | H18: =IF(G18>$O$6,"ACHIEVED","NOT ACHIEVED") -> NOT ACHIEVED
A19: JEANS-JACK | B19: 985 | C19: 456 | D19: 128 | E19: =SUM(B19:D19) -> 1569 | F19: 633 | G19: =F19*E19 -> 993177 | H19: =IF(G19>$O$6,"ACHIEVED","NOT ACHIEVED") -> ACHIEVED
A20: KURTA PAJAMA | B20: 754 | C20: 454 | D20: 748 | E20: =SUM(B20:D20) -> 1956 | F20: 234 | G20: =F20*E20 -> 457704 | H20: =IF(G20>$O$6,"ACHIEVED","NOT ACHIEVED") -> NOT ACHIEVED
... A22: LEE JEANS | B22: 532 | C22: 745 | D22: 743 | E22: =SUM(B22:D22) -> 2020 | F22: 633 | G22: =F22*E22 -> 1278660 | H22: =IF(G22>$O$6,"ACHIEVED","NOT ACHIEVED") -> ACHIEVED

Sheet BALANCE SHEET
A1: BALANCE SHEET
A3: YEAR | C3: CURRENT ACCOUNT | D3: CAPITAL ACCOUNT | E3: TOTAL=CURRENT ACCOUNT + CAPITAL ACCOUNT
A4: 1972 | B4: Credits | C4: 2095.8 | D4: 970.1 | E4: =SUM(C4,D4) -> 3065.9
B5: Debits | C5: 2497.3 | D5: 479.6 | E5: =SUM(C5,D5) -> 2976.9
B6: Net | C6: =SUM(C4:C5) -> 4593.1 | D6: =SUM(D4:D5) -> 1449.7 | E6: =SUM(C6,D6) -> 6042.8
A7: 1981-82 | B7: Credits | C7: 13577.5 | D7: 2615.6 | E7: =SUM(C7,D7) -> 16193.1
B8: Debits | C8: 15897.8 | D8: 2123.2 | E8: =SUM(C8,D8) -> 18021
B9: Net | C9: =SUM(C7:C8) -> 29475.3 | D9: =SUM(D7:D8) -> 4738.8 | E9: =SUM(C9,D9) -> 34214.1
A10: 1988-89 | B10: Credits | C10: 31573 | D10: 22454.9 | E10: =SUM(C10,D10) -> 54027.9
B11: Debits | C11: 43153.1 | D11: 10973.8 | E11: =SUM(C11,D11) -> 54126.9
B12: Net | C12: =SUM(C10:C11) -> 74726.1 | D12: =SUM(D9:D10) -> 27193.7 | E12: =SUM(C12,D12) -> 101919.8
A13: 1989-90 | B13: Credits | C13: 40719 | D13: 29361.8 | E13: =SUM(C13,D13) -> 70080.8
B14: Debits | C14: 52101.5 | D14: 17032.4 | E14: =SUM(C14,D14) -> 69133.9
B15: Net | C15: =SUM(C13:C14) -> 92820.5 | D15: =SUM(D13:D14) -> 46394.2 | E15: =SUM(C15,D15) -> 139214.7

Sheet MONTHLY REPORT
A1: MONTHLY SALES REPORT
A3: MONTH | B3: 1993 | C3: 1994 | D3: 1995 | E3: 1996 | F3: 1997 | G3: 1998 | H3: 1999 | I3: Monthly TotalFor 5 Years | J3: Avg. 5 years | K3: MONTHLY ELECTRIC SUPPLY
A4: JAN | B4: 345 | C4: 389 | D4: 367 | E4: 344 | F4: 129 | G4: 211 | H4: 280 | I4: =SUM(D4:H4) -> 1331 | J4: =AVERAGE(D4:H4) -> 266.2 | K4: =AVERAGE(Table3[[#This Row],[1993]:[1999]]) -> 295
A5: FEB | B5: 342 | C5: 345 | D5: 312 | E5: 311 | F5: 312 | G5: 200 | H5: 354 | I5: =SUM(D5:H5) -> 1489 | J5: =AVERAGE(D5:H5) -> 297.8 | K5: =AVERAGE(Table3[[#This Row],[1993]:[1999]]) -> 310.85714
A6: MAR | B6: 267 | C6: 367 | D6: 189 | E6: 280 | F6: 189 | G6: 134 | H6: 340 | I6: =SUM(D6:H6) -> 1132 | J6: =AVERAGE(D6:H6) -> 226.4 | K6: =AVERAGE(Table3[[#This Row],[1993]:[1999]]) -> 252.28571
A7: APR | B7: 367 | C7: 312 | D7: 254 | E7: 354 | F7: 254 | G7: 167 | H7: 245 | I7: =SUM(D7:H7) -> 1274 | J7: =AVERAGE(D7:H7) -> 254.8 | K7: =AVERAGE(Table3[[#This Row],[1993]:[1999]]) -> 279
A8: MAY | B8: 223 | C8: 189 | D8: 289 | E8: 340 | F8: 289 | G8: 390 | H8: 271 | I8: =SUM(D8:H8) -> 1579 | J8: =AVERAGE(D8:H8) -> 315.8 | K8: =AVERAGE(Table3[[#This Row],[1993]:[1999]]) -> 284.42857
A9: JUN | B9: 211 | C9: 254 | D9: 211 | E9: 245 | F9: 256 | G9: 289 | H9: 319 | I9: =SUM(D9:H9) -> 1320 | J9: =AVERAGE(D9:H9) -> 264 | K9: =AVERAGE(Table3[[#This Row],[1993]:[1999]]) -> 255
A10: JUL | B10: 200 | C10: 289 | D10: 200 | E10: 271 | F10: 217 | G10: 389 | H10: 254 | I10: =SUM(D10:H10) -> 1331 | J10: =AVERAGE(D10:H10) -> 266.2 | K10: =AVERAGE(Table3[[#This Row],[1993]:[1999]]) -> 260
A11: AUG | B11: 134 | C11: 256 | D11: 134 | E11: 319 | F11: 323 | G11: 345 | H11: 289 | I11: =SUM(D11:H11) -> 1410 | J11: =AVERAGE(D11:H11) -> 282 | K11: =AVERAGE(Table3[[#This Row],[1993]:[1999]]) -> 257.14286
A12: SEP | B12: 167 | C12: 217 | D12: 167 | E12: 254 | F12: 278 | G12: 367 | H12: 345 | I12: =SUM(D12:H12) -> 1411 | J12: =AVERAGE(D12:H12) -> 282.2 | K12: =AVERAGE(Table3[[#This Row],[1993]:[1999]]) -> 256.42857
A13: OCT | B13: 390 | C13: 219 | D13: 390 | E13: 289 | F13: 377 | G13: 312 | H13: 322 | I13: =SUM(D13:H13) -> 1690 | J13: =AVERAGE(D13:H13) -> 338 | K13: =AVERAGE(Table3[[#This Row],[1993]:[1999]]) -> 328.42857
A14: NOV | B14: 289 | C14: 367 | D14: 388 | E14: 211 | F14: 281 | G14: 189 | H14: 300 | I14: =SUM(D14:H14) -> 1369 | J14: =AVERAGE(D14:H14) -> 273.8 | K14: =AVERAGE(Table3[[#This Row],[1993]:[1999]]) -> 289.28571
A15: DEC | B15: 265 | C15: 345 | D15: 217 | E15: 200 | F15: 399 | G15: 134 | H15: 367 | I15: =SUM(D15:H15) -> 1317 | J15: =AVERAGE(D15:H15) -> 263.4 | K15: =AVERAGE(Table3[[#This Row],[1993]:[1999]]) -> 275.28571
... A27: DEC | B27: 265 | C27: 345 | D27: 217 | E27: 200 | F27: 399 | G27: 134 | H27: 367 | I27: =SUM(D27:H27) -> 1317 | J27: =AVERAGE(D27:H27) -> 263.4 | K27: =AVERAGE(Table3[[#This Row],[1993]:[1999]]) -> 275.28571
